pyuefivars/__init__.py
pyuefivars/aws.py
pyuefivars/aws_file.py
pyuefivars/aws_v0.py
pyuefivars/edk2.py
pyuefivars/efivarfs.py
pyuefivars/json.py
pyuefivars/varstore.py
uefivars-1.2.dist-info/LICENSE
uefivars-1.2.dist-info/METADATA
uefivars-1.2.dist-info/WHEEL
uefivars-1.2.dist-info/entry_points.txt
uefivars-1.2.dist-info/top_level.txt
uefivars-1.2.dist-info/RECORD
