Metadata-Version: 2.1
Name: uefivars
Version: 1.2
Summary: UEFI variable store tools
Home-page: https://github.com/awslabs/python-uefivars
Author: Amazon Web Services
Author-email: graf@amazon.com
Classifier: Programming Language :: Python :: 3
Classifier: License :: OSI Approved :: MIT License
Classifier: Operating System :: OS Independent
License-File: LICENSE
Requires-Dist: google-crc32c
Requires-Dist: deepdiff
